quickpt
