Metadata-Version: 2.1
Name: quickpt
Version: 0.0.7
Summary: For aggregating and visualizing variance, unique values and percent of missing values of features in any dataset.
Home-page: https://github.com/youssefsultan/quickpt
Author: Youssef Sultan
Author-email: youssefsultann@gmail.com
License: MIT
Keywords: visualize
Platform: UNKNOWN
Classifier: Programming Language :: Python :: 3
Classifier: License :: OSI Approved :: MIT License
Classifier: Operating System :: OS Independent
